cachephant-0.2.1.dist-info/METADATA
cachephant-0.2.1.dist-info/WHEEL
cachephant/__init__.py
cachephant/adapters/__init__.py
cachephant/adapters/db_sqlalchemy.py
cachephant/adapters/evictor.py
cachephant/adapters/filesystem.py
cachephant/adapters/hasher.py
cachephant/cache.py
cachephant/composite.py
cachephant/interfaces.py
cachephant-0.2.1.dist-info/RECORD
