Metadata-Version: 2.1
Name: cachephant
Version: 0.2.1
Home-page: https://github.com/cgebbe/cachephant
Author: Christian Gebbe
License: MIT
Project-URL: Homepage, https://github.com/cgebbe/cachephant
Requires-Python: >=3.11
Requires-Dist: pandas
Requires-Dist: deepdiff
Requires-Dist: fsspec
Requires-Dist: BearDataClass
Requires-Dist: SQLalchemy
